{
	"BP_Jelly1_C_0_DCD5940C4E71FEDAECDDB683AB775EC1": [
		{
			"Type": 1,
			"LocationX": 4377.5058240923572,
			"LocationY": 15472.38005554359,
			"LocationZ": 157.19066166859398,
			"ExtentX": 75,
			"ExtentY": 75,
			"ExtentZ": 75,
			"Yaw": 0,
			"Roll": -0,
			"Pitch": 0,
			"index": 0
		}
	],
	"BP_Jelly1_C_1_0CA96D124E88CF1AC7F51EBCFB9580F2": [
		{
			"Type": 1,
			"LocationX": 16447.190896608528,
			"LocationY": 7993.243783112739,
			"LocationZ": 137.48378887009306,
			"ExtentX": 75,
			"ExtentY": 75,
			"ExtentZ": 75,
			"Yaw": 0,
			"Roll": -0,
			"Pitch": 0,
			"index": 1
		}
	],
	"BP_Jelly1_C_10_71CA72AC406F9DA113274B891FCD5A31": [
		{
			"Type": 1,
			"LocationX": 11129.2558595221,
			"LocationY": 9544.8364098434067,
			"LocationZ": 138.22139939760956,
			"ExtentX": 75,
			"ExtentY": 75,
			"ExtentZ": 75,
			"Yaw": 0,
			"Roll": -0,
			"Pitch": 0,
			"index": 2
		}
	],
	"BP_Jelly1_C_11_7840C5EB46CA8090D9755484D5BA7C63": [
		{
			"Type": 1,
			"LocationX": 10014.867168618232,
			"LocationY": 18800.715222825325,
			"LocationZ": 137.48377341309259,
			"ExtentX": 75,
			"ExtentY": 75,
			"ExtentZ": 75,
			"Yaw": 0,
			"Roll": -0,
			"Pitch": 0,
			"index": 3
		}
	],
	"BP_Jelly1_C_12_C22E96BB4105EBF1F299AF945D0D4549": [
		{
			"Type": 1,
			"LocationX": 8492.5893076536759,
			"LocationY": 11472.07209647285,
			"LocationZ": 138.22133454116198,
			"ExtentX": 75,
			"ExtentY": 75,
			"ExtentZ": 75,
			"Yaw": 0,
			"Roll": -0,
			"Pitch": 0,
			"index": 4
		}
	],
	"BP_Jelly1_C_13_DC1EF7BD456935D85D2375B99D48507A": [
		{
			"Type": 1,
			"LocationX": 11173.63901874423,
			"LocationY": 9197.5992884071366,
			"LocationZ": 138.22140442691398,
			"ExtentX": 75,
			"ExtentY": 75,
			"ExtentZ": 75,
			"Yaw": 0,
			"Roll": -0,
			"Pitch": 0,
			"index": 5
		}
	],
	"BP_Jelly1_C_14_6AE50F3C49C72C87927282BFECFB1C9A": [
		{
			"Type": 1,
			"LocationX": 15637.311048770829,
			"LocationY": 17674.747721303011,
			"LocationZ": 137.25638235142452,
			"ExtentX": 75,
			"ExtentY": 75,
			"ExtentZ": 75,
			"Yaw": 0,
			"Roll": -0,
			"Pitch": 0,
			"index": 6
		}
	],
	"BP_Jelly1_C_15_7F6F77F441CE99AD179A28AB2FED3255": [
		{
			"Type": 1,
			"LocationX": 10574.31558802047,
			"LocationY": 8351.5064315991967,
			"LocationZ": 138.22139939760865,
			"ExtentX": 75,
			"ExtentY": 75,
			"ExtentZ": 75,
			"Yaw": 0,
			"Roll": -0,
			"Pitch": 0,
			"index": 7
		}
	],
	"BP_Jelly1_C_2_D7B9714D41F15C2D51F4C8A5D9FFF443": [
		{
			"Type": 1,
			"LocationX": 7465.6743980873907,
			"LocationY": 17827.254990373553,
			"LocationZ": 142.53069634932348,
			"ExtentX": 75,
			"ExtentY": 75,
			"ExtentZ": 75,
			"Yaw": 0,
			"Roll": -0,
			"Pitch": 0,
			"index": 8
		}
	],
	"BP_Jelly1_C_22_5AF5D47848C96BDF5383C79954526F26": [
		{
			"Type": 1,
			"LocationX": 12102.037081595217,
			"LocationY": 6368.0721247591455,
			"LocationZ": 133.96278513258625,
			"ExtentX": 75,
			"ExtentY": 75,
			"ExtentZ": 75,
			"Yaw": 0,
			"Roll": -0,
			"Pitch": 0,
			"index": 9
		}
	],
	"BP_Jelly1_C_23_87AD813E4D5035115A0B94ADC6A7C401": [
		{
			"Type": 1,
			"LocationX": 11852.037693602519,
			"LocationY": 6339.6894062159872,
			"LocationZ": 133.96278513258625,
			"ExtentX": 75,
			"ExtentY": 75,
			"ExtentZ": 75,
			"Yaw": 0,
			"Roll": -0,
			"Pitch": 0,
			"index": 10
		}
	],
	"BP_Jelly1_C_26_315CCD4E4EC20D9ECF05ADB0A7278230": [
		{
			"Type": 1,
			"LocationX": 11674.876909763863,
			"LocationY": 9249.5216673203267,
			"LocationZ": 133.96278513258716,
			"ExtentX": 75,
			"ExtentY": 75,
			"ExtentZ": 75,
			"Yaw": 0,
			"Roll": -0,
			"Pitch": 0,
			"index": 11
		}
	],
	"BP_Jelly1_C_27_B3BEDDAE4A55FC91484518B96EC2B623": [
		{
			"Type": 1,
			"LocationX": 11332.37828298575,
			"LocationY": 8718.7137960279033,
			"LocationZ": 133.96278513258716,
			"ExtentX": 75,
			"ExtentY": 75,
			"ExtentZ": 75,
			"Yaw": 0,
			"Roll": -0,
			"Pitch": 0,
			"index": 12
		}
	],
	"BP_Jelly1_C_30_6023F6B34F9EED3818A0F8A61039E8D6": [
		{
			"Type": 1,
			"LocationX": 15666.210984711008,
			"LocationY": 15207.201507264912,
			"LocationZ": 137.48397696500382,
			"ExtentX": 75,
			"ExtentY": 75,
			"ExtentZ": 75,
			"Yaw": 0,
			"Roll": -0,
			"Pitch": 0,
			"index": 13
		}
	],
	"BP_Jelly1_C_31_C49066424CCD1F6554D8B1AF53F300A6": [
		{
			"Type": 1,
			"LocationX": 11526.778184591893,
			"LocationY": 6782.433953784499,
			"LocationZ": 133.96278548718863,
			"ExtentX": 75,
			"ExtentY": 75,
			"ExtentZ": 75,
			"Yaw": 0,
			"Roll": -0,
			"Pitch": 0,
			"index": 14
		}
	],
	"BP_Jelly1_C_32_DDFA4F334519622A38496A8F734921F1": [
		{
			"Type": 1,
			"LocationX": 12186.985873394742,
			"LocationY": 6790.9730946307109,
			"LocationZ": 133.96278513258625,
			"ExtentX": 75,
			"ExtentY": 75,
			"ExtentZ": 75,
			"Yaw": 0,
			"Roll": -0,
			"Pitch": 0,
			"index": 15
		}
	],
	"BP_Jelly1_C_37_D2628FA44A79DCD10E66AE987D2C44F6": [
		{
			"Type": 1,
			"LocationX": 10067.827106940676,
			"LocationY": 12312.953188084592,
			"LocationZ": 137.4837791613549,
			"ExtentX": 75,
			"ExtentY": 75,
			"ExtentZ": 75,
			"Yaw": 0,
			"Roll": -0,
			"Pitch": 0,
			"index": 16
		}
	],
	"BP_Jelly1_C_38_F9BFE12742387D182A08C0BD56FA90E2": [
		{
			"Type": 1,
			"LocationX": 16801.459817281877,
			"LocationY": 13387.819994487429,
			"LocationZ": 137.48386721284805,
			"ExtentX": 75,
			"ExtentY": 75,
			"ExtentZ": 75,
			"Yaw": 0,
			"Roll": -0,
			"Pitch": 0,
			"index": 17
		}
	],
	"BP_Jelly1_C_39_555A002B473BD2CD08C95C80571FAF62": [
		{
			"Type": 1,
			"LocationX": 16467.239650836331,
			"LocationY": 13393.730291454558,
			"LocationZ": 137.48272744575399,
			"ExtentX": 75,
			"ExtentY": 75,
			"ExtentZ": 75,
			"Yaw": 0,
			"Roll": -0,
			"Pitch": 0,
			"index": 18
		}
	],
	"BP_Jelly1_C_4_6D07C8444C4F93B6FCC5A599836B09E0": [
		{
			"Type": 1,
			"LocationX": 10272.094331903414,
			"LocationY": 9815.1678065317901,
			"LocationZ": 138.22139733843466,
			"ExtentX": 75,
			"ExtentY": 75,
			"ExtentZ": 75,
			"Yaw": 0,
			"Roll": -0,
			"Pitch": 0,
			"index": 19
		}
	],
	"BP_Jelly1_C_40_B931AFFC4FFA1A7969C44A868FE631A9": [
		{
			"Type": 1,
			"LocationX": 11852.037683089928,
			"LocationY": 8474.518614081142,
			"LocationZ": 133.96278513258716,
			"ExtentX": 75,
			"ExtentY": 75,
			"ExtentZ": 75,
			"Yaw": 0,
			"Roll": -0,
			"Pitch": 0,
			"index": 20
		}
	],
	"BP_Jelly1_C_41_229F33104B4AAB40977E79A74F17BECB": [
		{
			"Type": 1,
			"LocationX": 11388.236105510872,
			"LocationY": 6339.6894202140275,
			"LocationZ": 133.9627851325867,
			"ExtentX": 75,
			"ExtentY": 75,
			"ExtentZ": 75,
			"Yaw": 0,
			"Roll": -0,
			"Pitch": 0,
			"index": 21
		}
	],
	"BP_Jelly1_C_42_E446A5574BAADE8120518FB04699FA49": [
		{
			"Type": 1,
			"LocationX": 15679.555193348026,
			"LocationY": 8372.2540557384345,
			"LocationZ": 137.48380327903095,
			"ExtentX": 75,
			"ExtentY": 75,
			"ExtentZ": 75,
			"Yaw": 0,
			"Roll": -0,
			"Pitch": 0,
			"index": 22
		}
	],
	"BP_Jelly1_C_43_D425964B4F1F1ADCCE4F889B46EF4830": [
		{
			"Type": 1,
			"LocationX": 10050.520574853697,
			"LocationY": 8738.4945615906545,
			"LocationZ": 137.17150375523016,
			"ExtentX": 75,
			"ExtentY": 75,
			"ExtentZ": 75,
			"Yaw": 0,
			"Roll": -0,
			"Pitch": 0,
			"index": 23
		}
	],
	"BP_Jelly1_C_44_2B8D743846375C45E4C996A610AB9F40": [
		{
			"Type": 1,
			"LocationX": 11852.037693205659,
			"LocationY": 6625.4867554065077,
			"LocationZ": 133.96278614538386,
			"ExtentX": 75,
			"ExtentY": 75,
			"ExtentZ": 75,
			"Yaw": 0,
			"Roll": -0,
			"Pitch": 0,
			"index": 24
		}
	],
	"BP_Jelly1_C_45_A4A7F582463289EE651ABEA70AE4DCFC": [
		{
			"Type": 1,
			"LocationX": 8939.891897292835,
			"LocationY": 13393.730275607471,
			"LocationZ": 137.48378887009625,
			"ExtentX": 75,
			"ExtentY": 75,
			"ExtentZ": 75,
			"Yaw": 0,
			"Roll": -0,
			"Pitch": 0,
			"index": 25
		}
	],
	"BP_Jelly1_C_46_C198FD6745DD2C04C284E9B8832273B2": [
		{
			"Type": 1,
			"LocationX": 16271.013525238275,
			"LocationY": 13694.033551450219,
			"LocationZ": 147.0668793741483,
			"ExtentX": 75,
			"ExtentY": 75,
			"ExtentZ": 75,
			"Yaw": 0,
			"Roll": -0,
			"Pitch": 0,
			"index": 26
		}
	],
	"BP_Jelly1_C_47_18A58D9D4C30E32D522061ADD26DC2CD": [
		{
			"Type": 1,
			"LocationX": 8293.6940222141493,
			"LocationY": 11784.220231400315,
			"LocationZ": 137.48378887009034,
			"ExtentX": 75,
			"ExtentY": 75,
			"ExtentZ": 75,
			"Yaw": 0,
			"Roll": -0,
			"Pitch": 0,
			"index": 27
		}
	],
	"BP_Jelly1_C_48_FA230288459905854D2F378036028720": [
		{
			"Type": 1,
			"LocationX": 7146.9322321039372,
			"LocationY": 16556.802175079611,
			"LocationZ": 151.57453192107724,
			"ExtentX": 75,
			"ExtentY": 75,
			"ExtentZ": 75,
			"Yaw": 0,
			"Roll": -0,
			"Pitch": 0,
			"index": 28
		}
	],
	"BP_Jelly1_C_49_053F836A4EB89A6CD021609B317A7B0C": [
		{
			"Type": 1,
			"LocationX": 3674.4080807161449,
			"LocationY": 12546.877203476157,
			"LocationZ": 137.48378887009034,
			"ExtentX": 75,
			"ExtentY": 75,
			"ExtentZ": 75,
			"Yaw": 0,
			"Roll": -0,
			"Pitch": 0,
			"index": 29
		}
	],
	"BP_Jelly1_C_50_6841289C41EA9425E06F8991923441FE": [
		{
			"Type": 1,
			"LocationX": 15071.571706134184,
			"LocationY": 14135.903963730476,
			"LocationZ": 137.48379969228284,
			"ExtentX": 75,
			"ExtentY": 75,
			"ExtentZ": 75,
			"Yaw": 0,
			"Roll": -0,
			"Pitch": 0,
			"index": 30
		}
	],
	"BP_Jelly1_C_51_2BF877C14AAFF55ABD1487955347ADBC": [
		{
			"Type": 1,
			"LocationX": 15276.861523973655,
			"LocationY": 15616.156091556204,
			"LocationZ": 137.48378887009034,
			"ExtentX": 75,
			"ExtentY": 75,
			"ExtentZ": 75,
			"Yaw": 0,
			"Roll": -0,
			"Pitch": 0,
			"index": 31
		}
	],
	"BP_Jelly1_C_52_ADF493114994D27A3E46929E136B07CD": [
		{
			"Type": 1,
			"LocationX": 15546.323919032529,
			"LocationY": 15958.55477722055,
			"LocationZ": 137.4837582314853,
			"ExtentX": 75,
			"ExtentY": 75,
			"ExtentZ": 75,
			"Yaw": 0,
			"Roll": -0,
			"Pitch": 0,
			"index": 32
		}
	],
	"BP_Jelly1_C_53_967E71E946A2B6F3E9C4898284D7BC11": [
		{
			"Type": 1,
			"LocationX": 12118.880844247933,
			"LocationY": 17931.650561842333,
			"LocationZ": 138.25825723838696,
			"ExtentX": 75,
			"ExtentY": 75,
			"ExtentZ": 75,
			"Yaw": 0,
			"Roll": -0,
			"Pitch": 0,
			"index": 33
		}
	],
	"BP_Jelly1_C_54_569C4CD14CCA83FF4668F6AB8F3608A9": [
		{
			"Type": 1,
			"LocationX": 4179.9213220811607,
			"LocationY": 17536.556571074336,
			"LocationZ": 137.48378887009034,
			"ExtentX": 75,
			"ExtentY": 75,
			"ExtentZ": 75,
			"Yaw": 0,
			"Roll": -0,
			"Pitch": 0,
			"index": 34
		}
	],
	"BP_Jelly1_C_55_0ADFDBD14E4B548E54347BBE2709E652": [
		{
			"Type": 1,
			"LocationX": 3988.1941517428054,
			"LocationY": 12329.419557145189,
			"LocationZ": 137.48378803183454,
			"ExtentX": 75,
			"ExtentY": 75,
			"ExtentZ": 75,
			"Yaw": 0,
			"Roll": -0,
			"Pitch": 0,
			"index": 35
		}
	],
	"BP_Jelly1_C_56_00A3B2434D5135BA9F2122B0BF0755D7": [
		{
			"Type": 1,
			"LocationX": 5647.342496305796,
			"LocationY": 12506.594831721855,
			"LocationZ": 137.48385245477471,
			"ExtentX": 75,
			"ExtentY": 75,
			"ExtentZ": 75,
			"Yaw": 0,
			"Roll": -0,
			"Pitch": 0,
			"index": 36
		}
	],
	"BP_Jelly1_C_57_BBE594834138548A4DCF4CB7E2D6FF52": [
		{
			"Type": 1,
			"LocationX": 3789.2001530037724,
			"LocationY": 16179.147385387989,
			"LocationZ": 137.48378887009216,
			"ExtentX": 75,
			"ExtentY": 75,
			"ExtentZ": 75,
			"Yaw": 0,
			"Roll": -0,
			"Pitch": 0,
			"index": 37
		}
	],
	"BP_Jelly1_C_58_38170D1C465B52B1125D8D910CF5BB99": [
		{
			"Type": 1,
			"LocationX": 5298.7575325524422,
			"LocationY": 17474.999208854984,
			"LocationZ": 137.48385372654042,
			"ExtentX": 75,
			"ExtentY": 75,
			"ExtentZ": 75,
			"Yaw": 0,
			"Roll": -0,
			"Pitch": 0,
			"index": 38
		}
	],
	"BP_Jelly1_C_59_FB591A1A4AA0F4332D5CE5A9D3870C0D": [
		{
			"Type": 1,
			"LocationX": 5324.6344807366131,
			"LocationY": 17765.574097582092,
			"LocationZ": 137.4838536826521,
			"ExtentX": 75,
			"ExtentY": 75,
			"ExtentZ": 75,
			"Yaw": 0,
			"Roll": -0,
			"Pitch": 0,
			"index": 39
		}
	],
	"BP_Jelly1_C_60_402700DB4EF7046FD78776960C5E13DA": [
		{
			"Type": 1,
			"LocationX": 9661.8248186146793,
			"LocationY": 13807.693522219581,
			"LocationZ": 137.48385532731299,
			"ExtentX": 75,
			"ExtentY": 75,
			"ExtentZ": 75,
			"Yaw": 0,
			"Roll": -0,
			"Pitch": 0,
			"index": 40
		}
	],
	"BP_Jelly1_C_61_A74B98C94D14FF87A1D00A85D166FEF4": [
		{
			"Type": 1,
			"LocationX": 5333.5483291432929,
			"LocationY": 17942.322914221946,
			"LocationZ": 137.48386289740773,
			"ExtentX": 75,
			"ExtentY": 75,
			"ExtentZ": 75,
			"Yaw": 0,
			"Roll": -0,
			"Pitch": 0,
			"index": 41
		}
	],
	"BP_Jelly1_C_62_2BE07816465DC9F155758398FD6F6B2E": [
		{
			"Type": 1,
			"LocationX": 9677.4414365829616,
			"LocationY": 13393.730291454556,
			"LocationZ": 137.48385266775944,
			"ExtentX": 75,
			"ExtentY": 75,
			"ExtentZ": 75,
			"Yaw": 0,
			"Roll": -0,
			"Pitch": 0,
			"index": 42
		}
	],
	"BP_Jelly1_C_63_E45D5CFC4C475EFEACBF539EFD4C4878": [
		{
			"Type": 1,
			"LocationX": 10698.65584241686,
			"LocationY": 12421.850405279532,
			"LocationZ": 153.44629376367189,
			"ExtentX": 75,
			"ExtentY": 75,
			"ExtentZ": 75,
			"Yaw": 0,
			"Roll": -0,
			"Pitch": 0,
			"index": 43
		}
	],
	"BP_Jelly1_C_64_98B5E0E3449372C61B5C92BAE91B0EF6": [
		{
			"Type": 1,
			"LocationX": 9546.9200717648182,
			"LocationY": 12200.972796638456,
			"LocationZ": 139.5222286363296,
			"ExtentX": 75,
			"ExtentY": 75,
			"ExtentZ": 75,
			"Yaw": 0,
			"Roll": -0,
			"Pitch": 0,
			"index": 44
		}
	],
	"BP_Jelly1_C_65_8AB94E0C48AB69EAA17252B4774000C3": [
		{
			"Type": 1,
			"LocationX": 9730.6587970395794,
			"LocationY": 11852.721501699065,
			"LocationZ": 138.22139920669542,
			"ExtentX": 75,
			"ExtentY": 75,
			"ExtentZ": 75,
			"Yaw": 0,
			"Roll": -0,
			"Pitch": 0,
			"index": 45
		}
	],
	"BP_Jelly1_C_66_ABED39BA45DDCCA1832DAF88104D090F": [
		{
			"Type": 1,
			"LocationX": 9730.6587970395794,
			"LocationY": 11472.07209647285,
			"LocationZ": 138.22139939761024,
			"ExtentX": 75,
			"ExtentY": 75,
			"ExtentZ": 75,
			"Yaw": 0,
			"Roll": -0,
			"Pitch": 0,
			"index": 46
		}
	],
	"BP_Jelly1_C_67_16C5187F4FA272C61A933388FA899BD6": [
		{
			"Type": 1,
			"LocationX": 10026.148355892397,
			"LocationY": 9815.1678065317901,
			"LocationZ": 138.22139939760865,
			"ExtentX": 75,
			"ExtentY": 75,
			"ExtentZ": 75,
			"Yaw": 0,
			"Roll": -0,
			"Pitch": 0,
			"index": 47
		}
	],
	"BP_Jelly1_C_7_AED77C624BE8C1298D1C91B52BC796B9": [
		{
			"Type": 1,
			"LocationX": 11144.040596078199,
			"LocationY": 9842.2671769929311,
			"LocationZ": 138.22139939760831,
			"ExtentX": 75,
			"ExtentY": 75,
			"ExtentZ": 75,
			"Yaw": 0,
			"Roll": -0,
			"Pitch": 0,
			"index": 48
		}
	],
	"BP_Jelly1_C_8_80BA48F546AB1E549BA99FBF6C416646": [
		{
			"Type": 1,
			"LocationX": 10170.571079396637,
			"LocationY": 14943.105759096063,
			"LocationZ": 137.48381076293884,
			"ExtentX": 75,
			"ExtentY": 75,
			"ExtentZ": 75,
			"Yaw": 0,
			"Roll": -0,
			"Pitch": 0,
			"index": 49
		}
	],
	"BP_Jelly1_C_9_C4A9ACC240433433E85E6F82DB2AF1F3": [
		{
			"Type": 1,
			"LocationX": 9661.8248186146793,
			"LocationY": 13606.134302545848,
			"LocationZ": 137.48385444569334,
			"ExtentX": 75,
			"ExtentY": 75,
			"ExtentZ": 75,
			"Yaw": 0,
			"Roll": -0,
			"Pitch": 0,
			"index": 50
		}
	]
}